{
  "avoir": 3752,
  "être": 3375,
  "religieux": 950,
  "musulman": 793,
  "tout": 788,
  "dialogue": 674,
  "ensuite": 637,
  "soi": 590,
  "pouvoir": 578,
  "faire": 546,
  "islam": 425,
  "dire": 419,
  "politique": 364,
  "plus": 357,
  "islamique": 351,
  "religion": 342,
  "pays": 328,
  "comme": 316,
  "autre": 313,
  "devoir": 298,
  "communauté": 264,
  "président": 257,
  "homme": 253,
  "vouloir": 234,
  "ivoire": 228,
  "côte": 226,
  "état": 219,
  "celui": 214,
  "falloir": 210,
  "paix": 208,
  "où": 192,
  "si": 191,
  "dieu": 190,
  "intégrisme": 187,
  "certain": 184,
  "prendre": 175,
  "grand": 173,
  "cela": 173,
  "savoir": 167,
  "entre": 166,
  "mosquée": 166,
  "el": 165,
  "imam": 165,
  "conseil": 163,
  "bien": 161,
  "hadj": 156,
  "aussi": 154,
  "monde": 153,
  "donc": 152,
  "dernier": 148,
  "aller": 148,
  "venir": 142,
  "national": 141,
  "contre": 140,
  "premier": 134,
  "donner": 130,
  "tel": 128,
  "car": 126,
  "cni": 125,
  "voir": 123,
  "deux": 119,
  "association": 118,
  "burkina": 116,
  "jour": 115,
  "croire": 114,
  "diaby": 114,
  "sans": 113,
  "arabe": 112,
  "depuis": 111,
  "dont": 110,
  "fait": 110,
  "mettre": 109,
  "bon": 107,
  "après": 107,
  "foi": 103,
  "selon": 103,
  "ivoirien": 103,
  "question": 102,
  "parce": 101,
  "personne": 100,
  "parti": 100,
  "organisation": 98,
  "très": 98,
  "chose": 98,
  "rdr": 98,
  "coran": 97,
  "culture": 97,
  "prophète": 96,
  "problème": 96,
  "toujours": 95,
  "an": 95,
  "lieu": 95,
  "ni": 95,
  "social": 94,
  "quelque": 94,
  "parler": 94,
  "église": 94,
  "temps": 93,
  "supérieur": 93,
  "ministre": 92
}