{
  "religieux": 963,
  "musulman": 823,
  "dialogue": 677,
  "ensuite": 637,
  "pouvoir": 604,
  "islam": 435,
  "islamique": 382,
  "politique": 366,
  "religion": 348,
  "pays": 335,
  "devoir": 297,
  "président": 268,
  "communauté": 268,
  "homme": 255,
  "vouloir": 243,
  "ivoire": 241,
  "côte": 238,
  "paix": 212,
  "falloir": 211,
  "imam": 198,
  "dieu": 194,
  "conseil": 192,
  "intégrisme": 190,
  "grand": 179,
  "etat": 179,
  "savoir": 177,
  "mosquée": 172,
  "national": 167,
  "bien": 167,
  "el": 164,
  "prendre": 164,
  "hadj": 159,
  "monde": 158,
  "aller": 149,
  "venir": 148,
  "association": 134,
  "cni": 133,
  "été": 121,
  "burkina": 118,
  "arabe": 117,
  "diaby": 116,
  "bon": 113,
  "ministre": 113,
  "celer": 110,
  "foi": 106,
  "organisation": 106,
  "ivoirien": 105,
  "mettre": 104,
  "question": 104,
  "parti": 103,
  "donner": 99,
  "rdr": 99,
  "prophète": 98,
  "coran": 98,
  "croire": 98,
  "problème": 98,
  "social": 97,
  "lieu": 97,
  "culture": 97,
  "supérieur": 95,
  "an": 95,
  "pdci": 92,
  "luire": 91,
  "chef": 91,
  "connaître": 89,
  "non": 89,
  "penser": 89,
  "femme": 89,
  "faso": 88,
  "vie": 87,
  "responsable": 87,
  "point": 85,
  "général": 84,
  "fidèle": 78,
  "acte": 78,
  "trouver": 78,
  "chrétien": 78,
  "vivre": 78,
  "droit": 78,
  "autorité": 77,
  "nom": 77,
  "comprendre": 76,
  "laïcité": 75,
  "créer": 74,
  "conférence": 72,
  "bénin": 71,
  "gouvernement": 71,
  "prière": 70,
  "csi": 70,
  "ailleurs": 69,
  "agir": 69,
  "cadre": 67,
  "permettre": 67,
  "enseignement": 67,
  "niveau": 67,
  "ensemble": 67,
  "nuit": 67,
  "fofana": 67,
  "bédié": 67,
  "esprit": 66,
  "appeler": 66,
  "jamais": 66,
  "organiser": 64,
  "force": 64,
  "allah": 64,
  "population": 63,
  "membre": 62,
  "mecque": 62,
  "saint": 62,
  "qu": 61,
  "société": 60,
  "beaucoup": 59,
  "formation": 59,
  "intégriste": 59,
  "public": 58,
  "position": 58,
  "travail": 58,
  "sens": 58,
  "place": 58,
  "pèlerin": 58,
  "développement": 57,
  "intérêt": 57,
  "eglise": 57,
  "international": 57,
  "peuple": 57,
  "important": 57,
  "siècle": 57,
  "passer": 57,
  "loi": 57,
  "partir": 57,
  "thème": 56,
  "part": 56,
  "afrique": 56,
  "tolérance": 56,
  "situation": 56,
  "burkinabè": 55,
  "intérieur": 55,
  "conscience": 54,
  "pèlerinage": 54,
  "rapport": 54,
  "groupe": 54,
  "représentant": 52,
  "rencontre": 52,
  "affaire": 52,
  "école": 52,
  "nord": 52,
  "liberté": 52,
  "recevoir": 51,
  "demander": 51,
  "moyen": 51,
  "koudouss": 51,
  "vrai": 49,
  "spirituel": 49,
  "compte": 49,
  "culturel": 49,
  "jeune": 49,
  "justice": 49,
  "monsieur": 49,
  "valeur": 48,
  "rôle": 48,
  "état": 48,
  "cours": 48,
  "nation": 48,
  "ouagadougou": 47,
  "catholique": 47,
  "occasion": 47,
  "fin": 47,
  "concerner": 46,
  "servir": 46,
  "poser": 46,
  "aucun": 46,
  "église": 46,
  "croyant": 45,
  "ordre": 45,
  "histoire": 45,
  "jeunesse": 45,
  "koné": 45,
  "frère": 44,
  "face": 44,
  "sein": 44,
  "pratique": 44,
  "devenir": 44,
  "mot": 44,
  "entendre": 44,
  "action": 43,
  "civilisation": 43,
  "mieux": 43,
  "famille": 43,
  "français": 43,
  "terme": 43,
  "république": 43,
  "unité": 42,
  "guerre": 42,
  "presse": 42,
  "moustapha": 42,
  "sembler": 42,
  "événement": 42,
  "rester": 41,
  "mal": 41,
  "nombre": 41
}