{
  "musulman": 1367,
  "religieux": 1102,
  "qu": 945,
  "dialogue": 697,
  "islam": 694,
  "ensuite": 650,
  "être": 582,
  "islamique": 553,
  "pays": 531,
  "politique": 518,
  "faire": 491,
  "religion": 486,
  "ivoire": 473,
  "président": 472,
  "côte": 465,
  "communauté": 451,
  "pouvoir": 399,
  "homme": 395,
  "vouloir": 371,
  "dieu": 342,
  "falloir": 335,
  "imam": 319,
  "paix": 289,
  "grand": 286,
  "que": 279,
  "mosquée": 266,
  "intégrisme": 264,
  "conseil": 264,
  "bien": 262,
  "etat": 261,
  "monde": 247,
  "prendre": 241,
  "el": 232,
  "savoir": 227,
  "contre": 221,
  "national": 220,
  "ivoirien": 216,
  "jour": 215,
  "hadj": 207,
  "aujourd": 205,
  "venir": 203,
  "dernier": 197,
  "cni": 197,
  "diaby": 193,
  "dire": 189,
  "ministre": 179,
  "devoir": 173,
  "association": 170,
  "été": 167,
  "bon": 166,
  "chef": 166,
  "voir": 165,
  "chose": 165,
  "temps": 162,
  "arabe": 162,
  "non": 160,
  "organisation": 160,
  "mettre": 159,
  "problème": 158,
  "donner": 154,
  "général": 150,
  "croire": 148,
  "supérieur": 147,
  "coran": 146,
  "question": 146,
  "prophète": 145,
  "foi": 144,
  "parti": 140,
  "social": 137,
  "lieu": 136,
  "vie": 135,
  "femme": 134,
  "an": 133,
  "congrès": 131,
  "comprendre": 130,
  "connaître": 128,
  "burkina": 127,
  "peuple": 127,
  "chrétien": 127,
  "aucun": 127,
  "beaucoup": 122,
  "rdr": 122,
  "vivre": 120,
  "fidèle": 119,
  "pdci": 119,
  "droit": 118,
  "Monsieur": 118,
  "bédié": 116,
  "csi": 116,
  "trouver": 115,
  "gouvernement": 115,
  "autorité": 115,
  "année": 114,
  "avoir": 114,
  "point": 113,
  "jamais": 113,
  "justice": 113,
  "prière": 112,
  "responsable": 112,
  "conférence": 111,
  "culture": 109,
  "créer": 108,
  "fois": 108,
  "cadre": 107,
  "nom": 107,
  "cas": 107,
  "agir": 107,
  "mecque": 107,
  "aller": 105,
  "saint": 104,
  "laïcité": 104,
  "afrique": 103,
  "état": 102,
  "acte": 101,
  "intégriste": 101,
  "moment": 100,
  "international": 98,
  "allah": 98,
  "organiser": 97,
  "part": 97,
  "force": 97,
  "ailleurs": 97,
  "société": 97,
  "faso": 96,
  "membre": 96,
  "niveau": 95,
  "abidjan": 95,
  "esprit": 94,
  "nord": 94,
  "frère": 93,
  "passer": 93,
  "développement": 93,
  "loi": 93,
  "république": 93,
  "devenir": 92,
  "demander": 92,
  "nuit": 92,
  "mondial": 91,
  "travers": 90,
  "affaire": 90,
  "permettre": 89,
  "nation": 89,
  "pèlerinage": 89,
  "nouveau": 88,
  "rencontre": 87,
  "public": 87,
  "appeler": 87,
  "place": 87,
  "tenir": 86,
  "vrai": 86,
  "population": 86,
  "pèlerin": 86,
  "ensemble": 85,
  "sens": 84,
  "tolérance": 84,
  "situation": 84,
  "fofana": 83,
  "travail": 82,
  "exemple": 82,
  "guerre": 81,
  "important": 81,
  "moyen": 81,
  "africain": 81,
  "intérieur": 80,
  "intérêt": 80,
  "compte": 80,
  "mois": 80,
  "enseignement": 79,
  "rien": 79,
  "liberté": 78,
  "siècle": 76,
  "ordre": 76,
  "thème": 75,
  "partir": 75,
  "événement": 74,
  "servir": 73,
  "occasion": 73,
  "presse": 73,
  "jeune": 73,
  "moustapha": 73,
  "raison": 72,
  "ici": 72,
  "bénin": 72,
  "penser": 72,
  "fin": 71,
  "recevoir": 71,
  "position": 71,
  "unité": 70,
  "mal": 70,
  "croyant": 70,
  "cause": 70,
  "formation": 70,
  "histoire": 70,
  "école": 70,
  "personne": 69,
  "conscience": 69,
  "heure": 68,
  "spirituel": 68,
  "mot": 68,
  "militant": 68
}